digiwise_search_tac/__init__.py
digiwise_search_tac/search_tac.py
search_tac-0.1.2.dist-info/METADATA
search_tac-0.1.2.dist-info/WHEEL
search_tac-0.1.2.dist-info/top_level.txt
search_tac-0.1.2.dist-info/RECORD
