Metadata-Version: 2.2
Name: search_tac
Version: 0.1.2
Summary: A TAC search tool using an Excel database
License: MIT
Classifier: Programming Language :: Python :: 3
Classifier: License :: OSI Approved :: MIT License
Classifier: Operating System :: OS Independent
Provides-Extra: dev
Requires-Dist: pytest; extra == "dev"
